to7m_exec.py
to7m_exec-0.0.0.dist-info/LICENSE.TXT
to7m_exec-0.0.0.dist-info/METADATA
to7m_exec-0.0.0.dist-info/WHEEL
to7m_exec-0.0.0.dist-info/top_level.txt
to7m_exec-0.0.0.dist-info/RECORD
